INSTALL.md
License
README.md
codecov.yml
config.ini
config.py
defense.py
functions.py
gp.py
implementation.py
main.py
plot.py
requirements.txt
rl.py
.github/workflows/main.yml
FAMEwork.egg-info/PKG-INFO
FAMEwork.egg-info/SOURCES.txt
FAMEwork.egg-info/dependency_links.txt
FAMEwork.egg-info/entry_points.txt
FAMEwork.egg-info/requires.txt
FAMEwork.egg-info/top_level.txt
data/gradient_boosting.pkl
data/lgbm_ember.pkl
data/lgbm_sorel.pkl
data/manipulate.py
data/pefeatures.py
data/section_names.txt
data/small_dll_imports.json
db/.gitkeep
db/rl/.gitkeep
docs/Makefile
docs/conf.py
docs/index.rst
docs/make.bat
samples/malware_set/.gitkeep
samples/mod/.gitkeep
samples/npz/.gitkeep
samples/rl/evaluation_set/.gitkeep
samples/successful/.gitkeep
samples/successful/detected/.gitkeep
samples/uap/.gitkeep
samples/unsuccessful/.gitkeep
tests/__init__.py
tests/test_main.py
FAMEwork-0.1.5.dist-info/METADATA
FAMEwork-0.1.5.dist-info/WHEEL
FAMEwork-0.1.5.dist-info/entry_points.txt
FAMEwork-0.1.5.dist-info/top_level.txt
FAMEwork-0.1.5.dist-info/RECORD
