Metadata-Version: 2.1
Name: FAMEwork
Version: 0.1.5
Summary: Framework for Adversarial Malware Evaluation
Home-page: https://github.com/zRapha/FAME
Author: Raphael Labaca Castro
Author-email: mail@rapha.ai
License: MPL-2.0
Platform: Fedora 30, Ubuntu 16
Requires-Dist: numpy (==1.19.0)
Requires-Dist: pandas (==0.25.0)
Requires-Dist: requests (==2.28.2)
Requires-Dist: scikit-learn (==0.21.2)
Requires-Dist: scipy (==1.5.1)
Requires-Dist: lief (==0.10.1)
Requires-Dist: lightgbm (==2.3.1)
Requires-Dist: joblib (==1.2.0)
Requires-Dist: chainer (==7.8.0)
Requires-Dist: chainerrl (==0.8.0)
Requires-Dist: pytest (==6.2.5)
Requires-Dist: coverage (==6.0)
Requires-Dist: tqdm (~=4.62.3)
Requires-Dist: sphinx (==4.2.0)
Requires-Dist: gym (~=0.19.0)
Requires-Dist: setuptools (~=57.0.0)
